textology/__init__.py
textology/apps.py
textology/awaitables.py
textology/dash_compat.py
textology/history.py
textology/logging.py
textology/pages.py
textology/parallel.py
textology/pytest_utils.py
textology/router.py
textology/test-template.html
textology/textual_utils.py
textology/observers/__init__.py
textology/observers/_dependencies.py
textology/observers/_exceptions.py
textology/observers/_managers.py
textology/widgets/__init__.py
textology/widgets/__init__.pyi
textology/widgets/_button.py
textology/widgets/_extensions.py
textology/widgets/_horizontal_menus.py
textology/widgets/_list_item.py
textology/widgets/_list_item_header.py
textology/widgets/_list_item_meta.py
textology/widgets/_list_view.py
textology/widgets/_location.py
textology/widgets/_modal_dialog.py
textology/widgets/_multi_select.py
textology/widgets/_page_container.py
textology/widgets/_popup_text.py
textology/widgets/_store.py
textology/widgets/_text.py
textology/widgets/_tree.py
textology/widgets/_textual/__init__.py
textology/widgets/_textual/_checkbox.py
textology/widgets/_textual/_collapsible.py
textology/widgets/_textual/_containers.py
textology/widgets/_textual/_content_switcher.py
textology/widgets/_textual/_data_table.py
textology/widgets/_textual/_digits.py
textology/widgets/_textual/_directory_tree.py
textology/widgets/_textual/_footer.py
textology/widgets/_textual/_header.py
textology/widgets/_textual/_label.py
textology/widgets/_textual/_loading_indicator.py
textology/widgets/_textual/_log.py
textology/widgets/_textual/_markdown.py
textology/widgets/_textual/_option_list.py
textology/widgets/_textual/_pretty.py
textology/widgets/_textual/_progress_bar.py
textology/widgets/_textual/_radio_button.py
textology/widgets/_textual/_radio_set.py
textology/widgets/_textual/_rich_log.py
textology/widgets/_textual/_rule.py
textology/widgets/_textual/_select.py
textology/widgets/_textual/_selection_list.py
textology/widgets/_textual/_sparkline.py
textology/widgets/_textual/_switch.py
textology-0.10.1.dist-info/licenses/LICENSE
textology-0.10.1.dist-info/METADATA
textology-0.10.1.dist-info/WHEEL
textology-0.10.1.dist-info/top_level.txt
textology-0.10.1.dist-info/RECORD
