Metadata-Version: 2.4
Name: textology
Version: 0.10.1
Summary: Textual extensions for creating Terminal User Interfaces
Author: David Fritz
License: MIT
Project-URL: Home, https://github.com/pyranha-labs/textology
Project-URL: Changelog, https://github.com/pyranha-labs/textology/releases
Project-URL: Issues, https://github.com/pyranha-labs/textology/issues
Keywords: cli,extensions,textual,tui,widgets
Platform: MacOS
Platform: Linux
Platform: Windows
Classifier: Development Status :: 4 - Beta
Classifier: Environment :: Console
Classifier: Intended Audience :: Developers
Classifier: License :: OSI Approved :: MIT License
Classifier: Programming Language :: Python
Classifier: Programming Language :: Python :: 3
Classifier: Programming Language :: Python :: 3 :: Only
Classifier: Programming Language :: Python :: 3.10
Classifier: Programming Language :: Python :: 3.11
Classifier: Topic :: Software Development
Classifier: Topic :: Software Development :: Libraries :: Application Frameworks
Classifier: Topic :: Software Development :: Widget Sets
Classifier: Typing :: Typed
Classifier: Operating System :: MacOS
Classifier: Operating System :: Microsoft :: Windows :: Windows 10
Classifier: Operating System :: Microsoft :: Windows :: Windows 11
Classifier: Operating System :: POSIX :: Linux
Requires-Python: >=3.10
License-File: LICENSE
Requires-Dist: textual<0.86.0,>=0.85.0
Provides-Extra: dev
Requires-Dist: pytest; extra == "dev"
Requires-Dist: pytest-asyncio; extra == "dev"
Requires-Dist: textual-dev; extra == "dev"
Dynamic: license-file
